{ "compressionlevel":-1,
 "height":18,
 "infinite":false,
 "layers":[
        {
         "draworder":"topdown",
         "id":3,
         "name":"chunk",
         "objects":[
                {
                 "height":0,
                 "id":7,
                 "name":"floor",
                 "point":true,
                 "rotation":0,
                 "type":"",
                 "visible":true,
                 "width":0,
                 "x":16,
                 "y":160
                }, 
                {
                 "height":0,
                 "id":10,
                 "name":"cact_1_big",
                 "point":true,
                 "rotation":0,
                 "type":"",
                 "visible":true,
                 "width":0,
                 "x":48,
                 "y":112
                }, 
                {
                 "height":0,
                 "id":11,
                 "name":"cact_2_big",
                 "point":true,
                 "rotation":0,
                 "type":"",
                 "visible":true,
                 "width":0,
                 "x":80,
                 "y":112
                }, 
                {
                 "height":0,
                 "id":12,
                 "name":"cact_3_big",
                 "point":true,
                 "rotation":0,
                 "type":"",
                 "visible":true,
                 "width":0,
                 "x":112,
                 "y":112
                }, 
                {
                 "height":0,
                 "id":13,
                 "name":"cact_4_big",
                 "point":true,
                 "rotation":0,
                 "type":"",
                 "visible":true,
                 "width":0,
                 "x":208,
                 "y":112
                }, 
                {
                 "height":0,
                 "id":14,
                 "name":"cact_5_big",
                 "point":true,
                 "rotation":0,
                 "type":"",
                 "visible":true,
                 "width":0,
                 "x":240,
                 "y":112
                }, 
                {
                 "height":0,
                 "id":15,
                 "name":"cact_6_big",
                 "point":true,
                 "rotation":0,
                 "type":"",
                 "visible":true,
                 "width":0,
                 "x":272,
                 "y":112
                }, 
                {
                 "height":0,
                 "id":16,
                 "name":"cact_7_big",
                 "point":true,
                 "rotation":0,
                 "type":"",
                 "visible":true,
                 "width":0,
                 "x":368,
                 "y":112
                }, 
                {
                 "height":0,
                 "id":17,
                 "name":"cact_8_big",
                 "point":true,
                 "rotation":0,
                 "type":"",
                 "visible":true,
                 "width":0,
                 "x":400,
                 "y":112
                }, 
                {
                 "height":0,
                 "id":18,
                 "name":"cact_9_big",
                 "point":true,
                 "rotation":0,
                 "type":"",
                 "visible":true,
                 "width":0,
                 "x":432,
                 "y":112
                }, 
                {
                 "height":0,
                 "id":19,
                 "name":"cact_1_small",
                 "point":true,
                 "rotation":0,
                 "type":"",
                 "visible":true,
                 "width":0,
                 "x":48,
                 "y":128
                }, 
                {
                 "height":0,
                 "id":20,
                 "name":"cact_2_small",
                 "point":true,
                 "rotation":0,
                 "type":"",
                 "visible":true,
                 "width":0,
                 "x":80,
                 "y":128
                }, 
                {
                 "height":0,
                 "id":21,
                 "name":"cact_3_small",
                 "point":true,
                 "rotation":0,
                 "type":"",
                 "visible":true,
                 "width":0,
                 "x":112,
                 "y":128
                }, 
                {
                 "height":0,
                 "id":22,
                 "name":"cact_4_small",
                 "point":true,
                 "rotation":0,
                 "type":"",
                 "visible":true,
                 "width":0,
                 "x":208,
                 "y":128
                }, 
                {
                 "height":0,
                 "id":23,
                 "name":"cact_5_small",
                 "point":true,
                 "rotation":0,
                 "type":"",
                 "visible":true,
                 "width":0,
                 "x":240,
                 "y":128
                }, 
                {
                 "height":0,
                 "id":24,
                 "name":"cact_6_small",
                 "point":true,
                 "rotation":0,
                 "type":"",
                 "visible":true,
                 "width":0,
                 "x":272,
                 "y":128
                }, 
                {
                 "height":0,
                 "id":25,
                 "name":"cact_7_small",
                 "point":true,
                 "rotation":0,
                 "type":"",
                 "visible":true,
                 "width":0,
                 "x":368,
                 "y":128
                }, 
                {
                 "height":0,
                 "id":26,
                 "name":"cact_8_small",
                 "point":true,
                 "rotation":0,
                 "type":"",
                 "visible":true,
                 "width":0,
                 "x":400,
                 "y":128
                }, 
                {
                 "height":0,
                 "id":27,
                 "name":"cact_9_small",
                 "point":true,
                 "rotation":0,
                 "type":"",
                 "visible":true,
                 "width":0,
                 "x":432,
                 "y":128
                }, 
                {
                 "height":0,
                 "id":107,
                 "name":"cact_big",
                 "point":true,
                 "rotation":0,
                 "type":"",
                 "visible":true,
                 "width":0,
                 "x":80,
                 "y":112
                }, 
                {
                 "height":0,
                 "id":108,
                 "name":"cact_big",
                 "point":true,
                 "rotation":0,
                 "type":"",
                 "visible":true,
                 "width":0,
                 "x":112,
                 "y":112
                }, 
                {
                 "height":0,
                 "id":109,
                 "name":"cact_big",
                 "point":true,
                 "rotation":0,
                 "type":"",
                 "visible":true,
                 "width":0,
                 "x":208,
                 "y":112
                }, 
                {
                 "height":0,
                 "id":110,
                 "name":"cact_big",
                 "point":true,
                 "rotation":0,
                 "type":"",
                 "visible":true,
                 "width":0,
                 "x":240,
                 "y":112
                }, 
                {
                 "height":0,
                 "id":111,
                 "name":"cact_big",
                 "point":true,
                 "rotation":0,
                 "type":"",
                 "visible":true,
                 "width":0,
                 "x":272,
                 "y":112
                }, 
                {
                 "height":0,
                 "id":112,
                 "name":"cact_big",
                 "point":true,
                 "rotation":0,
                 "type":"",
                 "visible":true,
                 "width":0,
                 "x":368,
                 "y":112
                }, 
                {
                 "height":0,
                 "id":113,
                 "name":"cact_big",
                 "point":true,
                 "rotation":0,
                 "type":"",
                 "visible":true,
                 "width":0,
                 "x":400,
                 "y":112
                }],
         "opacity":1,
         "type":"objectgroup",
         "visible":true,
         "x":0,
         "y":0
        }, 
        {
         "data":[32, 32, 32, 32, 32, 32, 32, 32, 32, 32, 32, 32, 32, 32, 32, 32, 32, 32, 32, 32, 32, 32, 32, 32, 32, 32, 32, 32, 32, 32, 32, 32,
            32, 32, 32, 32, 32, 32, 32, 32, 32, 32, 32, 32, 32, 32, 32, 32, 32, 32, 32, 32, 32, 32, 32, 32, 32, 32, 32, 32, 32, 32, 32, 32,
            32, 24, 32, 24, 32, 24, 32, 24, 32, 24, 32, 24, 32, 24, 32, 24, 32, 24, 32, 24, 32, 24, 32, 24, 32, 24, 32, 24, 32, 24, 32, 24,
            24, 32, 24, 32, 24, 32, 24, 32, 24, 32, 24, 32, 24, 32, 24, 32, 24, 32, 24, 32, 24, 32, 24, 32, 24, 32, 24, 32, 24, 32, 24, 32,
            24, 24, 24, 24, 24, 24, 24, 24, 24, 24, 24, 24, 24, 24, 24, 24, 24, 24, 24, 24, 24, 24, 24, 24, 24, 24, 24, 24, 24, 24, 24, 24,
            16, 16, 16, 16, 16, 16, 16, 16, 16, 16, 16, 16, 16, 16, 16, 16, 16, 16, 16, 16, 16, 16, 16, 16, 16, 16, 16, 16, 16, 16, 16, 16,
            16, 16, 16, 16, 16, 16, 16, 16, 16, 16, 16, 16, 16, 16, 16, 16, 16, 16, 16, 16, 16, 16, 16, 16, 16, 16, 16, 16, 16, 16, 16, 16,
            8, 8, 8, 8, 8, 8, 8, 8, 8, 8, 8, 8, 8, 8, 8, 8, 8, 8, 8, 8, 8, 8, 8, 8, 8, 8, 8, 8, 8, 8, 8, 8,
            8, 8, 8, 8, 8, 8, 8, 8, 8, 8, 8, 8, 8, 8, 8, 8, 8, 8, 8, 8, 8, 8, 8, 8, 8, 8, 8, 8, 8, 8, 8, 8,
            8, 8, 8, 8, 8, 8, 8, 8, 8, 8, 8, 8, 8, 8, 8, 8, 8, 8, 8, 8, 8, 8, 8, 8, 8, 8, 8, 8, 8, 8, 8, 8,
            8, 8, 8, 8, 8, 8, 8, 8, 8, 8, 8, 8, 8, 8, 8, 8, 8, 8, 8, 8, 8, 8, 8, 8, 8, 8, 8, 8, 8, 8, 8, 8,
            16, 16, 16, 16, 16, 16, 16, 16, 16, 16, 16, 16, 16, 16, 16, 16, 16, 16, 16, 16, 16, 16, 16, 16, 16, 16, 16, 16, 16, 16, 16, 16,
            16, 16, 16, 16, 16, 16, 16, 16, 16, 16, 16, 16, 16, 16, 16, 16, 16, 16, 16, 16, 16, 16, 16, 16, 16, 16, 16, 16, 16, 16, 16, 16,
            24, 24, 24, 24, 24, 24, 24, 24, 24, 24, 24, 24, 24, 24, 24, 24, 24, 24, 24, 24, 24, 24, 24, 24, 24, 24, 24, 24, 24, 24, 24, 24,
            24, 32, 24, 32, 24, 32, 24, 32, 24, 32, 24, 32, 24, 32, 24, 32, 24, 32, 24, 32, 24, 32, 24, 32, 24, 32, 24, 32, 24, 32, 24, 32,
            32, 24, 32, 24, 32, 24, 32, 24, 32, 24, 32, 24, 32, 24, 32, 24, 32, 24, 32, 24, 32, 24, 32, 24, 32, 24, 32, 24, 32, 24, 32, 24,
            32, 32, 32, 32, 32, 32, 32, 32, 32, 32, 32, 32, 32, 32, 32, 32, 32, 32, 32, 32, 32, 32, 32, 32, 32, 32, 32, 32, 32, 32, 32, 32,
            32, 32, 32, 32, 32, 32, 32, 32, 32, 32, 32, 32, 32, 32, 32, 32, 32, 32, 32, 32, 32, 32, 32, 32, 32, 32, 32, 32, 32, 32, 32, 32],
         "height":18,
         "id":5,
         "name":"bg_far",
         "opacity":1,
         "type":"tilelayer",
         "visible":false,
         "width":32,
         "x":0,
         "y":0
        }, 
        {
         "data":[0, 0, 1073741875, 1073741876, 0, 0, 0, 0, 0, 1073741873, 1073741874, 0, 0, 0, 0, 1073741875, 1073741876, 0, 0, 0, 0, 1073741881, 1073741882, 0, 0, 0, 0, 0, 0, 1073741875, 1073741876, 0,
            0, 0, 1073741873, 1073741874, 0, 0, 0, 0, 0, 1073741865, 1073741866, 0, 0, 0, 0, 1073741881, 1073741882, 0, 0, 0, 0, 1073741873, 1073741874, 0, 0, 0, 0, 0, 0, 1073741881, 1073741882, 0,
            0, 0, 1073741865, 1073741866, 0, 0, 0, 0, 0, 1073741857, 1073741858, 0, 0, 0, 0, 1073741875, 1073741876, 0, 0, 0, 0, 1073741865, 1073741866, 0, 0, 0, 0, 0, 0, 1073741875, 1073741876, 0,
            0, 0, 1073741883, 1073741884, 0, 0, 0, 0, 0, 1073741849, 1073741850, 0, 0, 0, 0, 1073741881, 1073741882, 0, 0, 0, 0, 33, 34, 0, 0, 0, 0, 0, 0, 1073741873, 1073741874, 0,
            0, 0, 1073741883, 1073741884, 0, 0, 0, 0, 0, 0, 0, 0, 0, 0, 0, 1073741873, 1073741874, 0, 0, 0, 0, 33, 34, 0, 0, 0, 0, 0, 0, 1073741865, 1073741866, 0,
            0, 0, 1073741883, 1073741884, 0, 0, 0, 0, 0, 0, 0, 0, 0, 0, 0, 1073741865, 1073741866, 0, 0, 0, 0, 1073741883, 1073741884, 0, 0, 0, 0, 0, 0, 33, 34, 0,
            0, 0, 1073741883, 1073741884, 0, 0, 0, 0, 0, 0, 0, 0, 0, 0, 0, 1073741849, 1073741850, 0, 0, 0, 0, 33, 34, 0, 0, 0, 0, 0, 0, 33, 34, 0,
            0, 0, 1073741849, 1073741850, 0, 0, 0, 0, 0, 0, 0, 0, 0, 0, 0, 0, 0, 0, 0, 0, 0, 1073741849, 1073741850, 0, 0, 0, 0, 0, 0, 1073741849, 1073741850, 0,
            0, 0, 0, 0, 0, 0, 25, 26, 0, 0, 0, 0, 0, 0, 0, 0, 0, 0, 0, 0, 0, 0, 0, 0, 0, 0, 25, 26, 0, 0, 0, 0,
            0, 0, 0, 0, 0, 0, 33, 34, 0, 0, 25, 26, 0, 0, 0, 0, 0, 0, 0, 0, 0, 0, 0, 0, 0, 0, 33, 34, 0, 0, 0, 0,
            25, 26, 0, 0, 0, 0, 41, 42, 0, 0, 33, 34, 0, 0, 0, 0, 0, 0, 0, 0, 0, 0, 0, 0, 0, 0, 33, 34, 0, 0, 0, 0,
            33, 34, 0, 0, 0, 0, 49, 50, 0, 0, 59, 60, 0, 0, 0, 0, 0, 0, 0, 0, 0, 0, 0, 0, 0, 0, 41, 42, 0, 0, 0, 0,
            33, 34, 0, 0, 0, 0, 57, 58, 0, 0, 33, 34, 0, 0, 0, 0, 0, 0, 0, 0, 0, 0, 0, 0, 0, 0, 49, 50, 0, 0, 0, 0,
            41, 42, 0, 0, 0, 0, 51, 52, 0, 0, 41, 42, 0, 0, 0, 0, 0, 0, 0, 25, 26, 0, 0, 0, 0, 0, 57, 58, 0, 0, 0, 0,
            49, 50, 0, 0, 0, 0, 57, 58, 0, 0, 49, 50, 0, 0, 0, 0, 0, 0, 0, 33, 34, 0, 0, 0, 0, 0, 51, 52, 0, 0, 0, 0,
            57, 58, 0, 0, 0, 0, 51, 52, 0, 0, 51, 52, 0, 0, 0, 0, 0, 0, 0, 41, 42, 0, 0, 0, 0, 0, 57, 58, 0, 0, 0, 0,
            57, 58, 0, 0, 0, 0, 57, 58, 0, 0, 57, 58, 0, 0, 0, 0, 0, 0, 0, 49, 50, 0, 0, 0, 0, 0, 51, 52, 0, 0, 0, 0,
            51, 52, 0, 0, 0, 0, 51, 52, 0, 0, 51, 52, 0, 0, 0, 0, 0, 0, 0, 57, 58, 0, 0, 0, 0, 0, 57, 58, 0, 0, 0, 0],
         "height":18,
         "id":6,
         "name":"bg_buildings",
         "opacity":1,
         "type":"tilelayer",
         "visible":false,
         "width":32,
         "x":0,
         "y":0
        }, 
        {
         "data":[0, 0, 0, 0, 0, 0, 0, 0, 0, 0, 0, 0, 0, 0, 0, 0, 0, 0, 0, 0, 0, 0, 0, 0, 0, 0, 0, 0, 0, 0, 0, 0,
            0, 0, 0, 0, 0, 0, 0, 0, 0, 0, 0, 0, 0, 0, 0, 0, 0, 0, 0, 0, 0, 0, 0, 0, 0, 0, 0, 0, 0, 0, 0, 0,
            0, 0, 0, 0, 0, 0, 0, 0, 0, 0, 0, 0, 0, 0, 0, 0, 0, 0, 0, 0, 0, 0, 0, 0, 0, 0, 1073741851, 1073741852, 0, 0, 0, 0,
            0, 0, 0, 0, 0, 0, 0, 0, 0, 0, 0, 0, 0, 0, 0, 0, 0, 0, 0, 0, 0, 0, 0, 0, 0, 0, 0, 0, 0, 0, 0, 0,
            0, 0, 0, 0, 0, 0, 0, 0, 0, 0, 0, 1073741851, 1073741852, 0, 0, 0, 0, 0, 0, 0, 0, 0, 0, 0, 0, 0, 0, 0, 0, 0, 0, 0,
            0, 0, 0, 0, 0, 0, 0, 0, 0, 0, 0, 0, 0, 0, 0, 0, 0, 0, 0, 0, 0, 0, 0, 0, 0, 0, 0, 0, 0, 0, 0, 0,
            0, 0, 0, 0, 0, 0, 0, 0, 0, 0, 0, 0, 0, 0, 0, 0, 0, 0, 0, 0, 0, 0, 0, 0, 0, 0, 0, 0, 0, 0, 0, 0,
            0, 0, 0, 0, 0, 0, 0, 0, 0, 0, 0, 0, 0, 0, 0, 0, 0, 0, 0, 0, 0, 0, 0, 0, 0, 0, 0, 0, 0, 0, 0, 0,
            0, 0, 0, 0, 0, 0, 0, 0, 0, 0, 0, 0, 0, 0, 0, 0, 0, 0, 0, 0, 0, 0, 0, 0, 0, 0, 0, 0, 0, 0, 0, 0,
            0, 0, 0, 0, 0, 0, 0, 0, 0, 0, 0, 0, 0, 0, 0, 0, 0, 0, 0, 0, 0, 27, 28, 0, 0, 0, 0, 0, 0, 0, 0, 0,
            0, 0, 0, 0, 0, 0, 0, 0, 0, 0, 0, 0, 0, 0, 0, 0, 0, 0, 0, 0, 0, 0, 0, 0, 0, 0, 0, 0, 0, 0, 0, 0,
            0, 0, 0, 0, 0, 0, 0, 0, 0, 0, 0, 0, 0, 0, 0, 0, 0, 0, 0, 0, 0, 0, 0, 0, 0, 0, 0, 0, 0, 0, 0, 0,
            0, 0, 27, 28, 0, 0, 0, 0, 0, 0, 0, 0, 0, 0, 0, 0, 0, 0, 0, 0, 0, 0, 0, 0, 0, 0, 0, 0, 0, 0, 0, 0,
            0, 0, 0, 0, 0, 0, 0, 0, 0, 0, 0, 0, 0, 0, 0, 0, 0, 0, 0, 0, 0, 0, 0, 0, 0, 0, 0, 0, 0, 0, 0, 0,
            0, 0, 0, 0, 0, 0, 0, 0, 0, 0, 0, 0, 0, 0, 0, 0, 0, 0, 0, 0, 0, 0, 0, 0, 0, 0, 0, 0, 0, 27, 28, 0,
            0, 0, 0, 0, 0, 0, 0, 0, 0, 0, 0, 0, 0, 0, 0, 0, 0, 0, 0, 0, 0, 0, 0, 0, 0, 0, 0, 0, 0, 0, 0, 0,
            0, 0, 0, 0, 0, 0, 0, 0, 0, 0, 0, 0, 0, 0, 0, 0, 0, 0, 0, 0, 0, 0, 0, 0, 0, 0, 0, 0, 0, 0, 0, 0,
            0, 0, 0, 0, 0, 0, 0, 0, 0, 0, 0, 0, 0, 0, 0, 0, 0, 0, 0, 0, 0, 0, 0, 0, 0, 0, 0, 0, 0, 0, 0, 0],
         "height":18,
         "id":7,
         "name":"bg_ships",
         "opacity":1,
         "type":"tilelayer",
         "visible":false,
         "width":32,
         "x":0,
         "y":0
        }, 
        {
         "data":[0, 0, 0, 0, 0, 0, 0, 0, 0, 0, 0, 0, 0, 0, 0, 0, 0, 0, 0, 0, 0, 0, 0, 0, 0, 0, 0, 0, 0, 0, 0, 0,
            0, 0, 0, 0, 0, 0, 0, 0, 0, 0, 0, 0, 0, 0, 0, 0, 0, 0, 0, 0, 0, 0, 0, 0, 0, 0, 0, 0, 0, 0, 0, 0,
            0, 0, 0, 0, 0, 0, 0, 0, 0, 0, 0, 0, 0, 0, 0, 0, 0, 0, 0, 0, 0, 0, 0, 0, 0, 0, 0, 0, 0, 0, 0, 0,
            0, 0, 0, 0, 0, 0, 0, 0, 0, 0, 0, 0, 0, 0, 0, 0, 0, 0, 0, 0, 0, 0, 0, 0, 0, 0, 0, 0, 0, 0, 0, 0,
            0, 0, 0, 0, 0, 0, 0, 0, 0, 0, 0, 0, 0, 0, 0, 0, 0, 0, 0, 0, 0, 0, 0, 0, 0, 0, 0, 0, 0, 0, 0, 0,
            0, 0, 0, 0, 0, 0, 0, 0, 0, 0, 0, 0, 0, 0, 0, 0, 0, 0, 0, 0, 0, 0, 0, 0, 0, 0, 0, 0, 0, 0, 0, 0,
            0, 0, 0, 0, 0, 0, 0, 0, 0, 0, 0, 0, 0, 0, 0, 0, 0, 0, 0, 0, 0, 0, 0, 0, 0, 0, 0, 0, 0, 0, 0, 0,
            0, 0, 0, 14, 15, 0, 0, 0, 0, 0, 0, 0, 0, 0, 0, 0, 0, 0, 0, 0, 0, 0, 0, 0, 0, 0, 0, 14, 15, 0, 0, 0,
            0, 0, 0, 22, 23, 12, 13, 12, 13, 0, 0, 0, 0, 12, 13, 12, 13, 12, 13, 0, 0, 0, 0, 12, 13, 12, 13, 22, 23, 0, 0, 0,
            0, 0, 0, 30, 31, 20, 21, 20, 21, 0, 0, 0, 0, 20, 21, 20, 21, 20, 21, 0, 0, 0, 0, 20, 21, 20, 21, 30, 31, 0, 0, 0,
            0, 53, 54, 54, 54, 54, 54, 54, 54, 54, 55, 53, 54, 54, 54, 54, 54, 54, 54, 54, 55, 53, 54, 54, 54, 54, 54, 54, 54, 54, 55, 0,
            0, 61, 62, 62, 62, 62, 62, 62, 62, 62, 63, 61, 62, 62, 62, 62, 62, 62, 62, 62, 63, 61, 62, 62, 62, 62, 62, 62, 62, 62, 63, 0,
            0, 64, 64, 0, 0, 0, 0, 0, 0, 0, 64, 64, 0, 0, 0, 0, 0, 0, 0, 0, 64, 64, 0, 0, 0, 0, 0, 0, 0, 64, 64, 0,
            0, 64, 64, 0, 0, 0, 0, 0, 0, 0, 64, 64, 0, 0, 0, 0, 0, 0, 0, 0, 64, 64, 0, 0, 0, 0, 0, 0, 0, 64, 64, 0,
            0, 64, 64, 0, 0, 0, 0, 0, 0, 0, 64, 64, 0, 0, 0, 0, 0, 0, 0, 0, 64, 64, 0, 0, 0, 0, 0, 0, 0, 64, 64, 0,
            0, 64, 64, 0, 0, 0, 0, 0, 0, 0, 64, 64, 0, 0, 0, 0, 0, 0, 0, 0, 64, 64, 0, 0, 0, 0, 0, 0, 0, 64, 64, 0,
            0, 64, 64, 0, 0, 0, 0, 0, 0, 0, 64, 64, 0, 0, 0, 0, 0, 0, 0, 0, 64, 64, 0, 0, 0, 0, 0, 0, 0, 64, 64, 0,
            0, 64, 64, 0, 0, 0, 0, 0, 0, 0, 64, 64, 0, 0, 0, 0, 0, 0, 0, 0, 64, 64, 0, 0, 0, 0, 0, 0, 0, 64, 64, 0],
         "height":18,
         "id":2,
         "name":"bottom_mockup",
         "opacity":1,
         "type":"tilelayer",
         "visible":false,
         "width":32,
         "x":0,
         "y":0
        }],
 "nextlayerid":8,
 "nextobjectid":115,
 "orientation":"orthogonal",
 "renderorder":"right-down",
 "tiledversion":"1.11.2",
 "tileheight":16,
 "tilesets":[
        {
         "columns":8,
         "firstgid":1,
         "image":"space-station-tiles.png",
         "imageheight":128,
         "imagewidth":128,
         "margin":0,
         "name":"space-station-tiles",
         "spacing":0,
         "tilecount":64,
         "tileheight":16,
         "tiles":[
                {
                 "id":0,
                 "properties":[
                        {
                         "name":"collides",
                         "type":"bool",
                         "value":true
                        }, 
                        {
                         "name":"kills",
                         "type":"bool",
                         "value":false
                        }]
                }, 
                {
                 "id":1,
                 "properties":[
                        {
                         "name":"collides",
                         "type":"bool",
                         "value":true
                        }, 
                        {
                         "name":"kills",
                         "type":"bool",
                         "value":false
                        }]
                }, 
                {
                 "id":2,
                 "properties":[
                        {
                         "name":"collides",
                         "type":"bool",
                         "value":true
                        }, 
                        {
                         "name":"kills",
                         "type":"bool",
                         "value":false
                        }]
                }, 
                {
                 "id":3,
                 "properties":[
                        {
                         "name":"collides",
                         "type":"bool",
                         "value":true
                        }, 
                        {
                         "name":"kills",
                         "type":"bool",
                         "value":false
                        }]
                }, 
                {
                 "id":4,
                 "properties":[
                        {
                         "name":"collides",
                         "type":"bool",
                         "value":true
                        }, 
                        {
                         "name":"kills",
                         "type":"bool",
                         "value":false
                        }]
                }, 
                {
                 "id":5,
                 "properties":[
                        {
                         "name":"collides",
                         "type":"bool",
                         "value":true
                        }, 
                        {
                         "name":"kills",
                         "type":"bool",
                         "value":false
                        }]
                }, 
                {
                 "id":6,
                 "properties":[
                        {
                         "name":"collides",
                         "type":"bool",
                         "value":true
                        }, 
                        {
                         "name":"kills",
                         "type":"bool",
                         "value":false
                        }]
                }, 
                {
                 "id":7,
                 "properties":[
                        {
                         "name":"collides",
                         "type":"bool",
                         "value":false
                        }, 
                        {
                         "name":"kills",
                         "type":"bool",
                         "value":false
                        }]
                }, 
                {
                 "id":8,
                 "properties":[
                        {
                         "name":"collides",
                         "type":"bool",
                         "value":true
                        }, 
                        {
                         "name":"kills",
                         "type":"bool",
                         "value":false
                        }]
                }, 
                {
                 "id":9,
                 "properties":[
                        {
                         "name":"collides",
                         "type":"bool",
                         "value":true
                        }, 
                        {
                         "name":"kills",
                         "type":"bool",
                         "value":false
                        }]
                }, 
                {
                 "id":10,
                 "properties":[
                        {
                         "name":"collides",
                         "type":"bool",
                         "value":true
                        }, 
                        {
                         "name":"kills",
                         "type":"bool",
                         "value":false
                        }]
                }, 
                {
                 "id":11,
                 "properties":[
                        {
                         "name":"collides",
                         "type":"bool",
                         "value":false
                        }, 
                        {
                         "name":"kills",
                         "type":"bool",
                         "value":true
                        }]
                }, 
                {
                 "id":12,
                 "properties":[
                        {
                         "name":"collides",
                         "type":"bool",
                         "value":false
                        }, 
                        {
                         "name":"kills",
                         "type":"bool",
                         "value":true
                        }]
                }, 
                {
                 "id":13,
                 "properties":[
                        {
                         "name":"collides",
                         "type":"bool",
                         "value":false
                        }, 
                        {
                         "name":"kills",
                         "type":"bool",
                         "value":true
                        }]
                }, 
                {
                 "id":14,
                 "properties":[
                        {
                         "name":"collides",
                         "type":"bool",
                         "value":false
                        }, 
                        {
                         "name":"kills",
                         "type":"bool",
                         "value":true
                        }]
                }, 
                {
                 "id":15,
                 "properties":[
                        {
                         "name":"collides",
                         "type":"bool",
                         "value":false
                        }, 
                        {
                         "name":"kills",
                         "type":"bool",
                         "value":false
                        }]
                }, 
                {
                 "id":16,
                 "properties":[
                        {
                         "name":"collides",
                         "type":"bool",
                         "value":true
                        }, 
                        {
                         "name":"kills",
                         "type":"bool",
                         "value":false
                        }]
                }, 
                {
                 "id":17,
                 "properties":[
                        {
                         "name":"collides",
                         "type":"bool",
                         "value":true
                        }, 
                        {
                         "name":"kills",
                         "type":"bool",
                         "value":false
                        }]
                }, 
                {
                 "id":18,
                 "properties":[
                        {
                         "name":"collides",
                         "type":"bool",
                         "value":true
                        }, 
                        {
                         "name":"kills",
                         "type":"bool",
                         "value":false
                        }]
                }, 
                {
                 "id":19,
                 "properties":[
                        {
                         "name":"collides",
                         "type":"bool",
                         "value":false
                        }, 
                        {
                         "name":"kills",
                         "type":"bool",
                         "value":true
                        }]
                }, 
                {
                 "id":20,
                 "properties":[
                        {
                         "name":"collides",
                         "type":"bool",
                         "value":false
                        }, 
                        {
                         "name":"kills",
                         "type":"bool",
                         "value":true
                        }]
                }, 
                {
                 "id":21,
                 "properties":[
                        {
                         "name":"collides",
                         "type":"bool",
                         "value":false
                        }, 
                        {
                         "name":"kills",
                         "type":"bool",
                         "value":true
                        }]
                }, 
                {
                 "id":22,
                 "properties":[
                        {
                         "name":"collides",
                         "type":"bool",
                         "value":false
                        }, 
                        {
                         "name":"kills",
                         "type":"bool",
                         "value":true
                        }]
                }, 
                {
                 "id":23,
                 "properties":[
                        {
                         "name":"collides",
                         "type":"bool",
                         "value":false
                        }, 
                        {
                         "name":"kills",
                         "type":"bool",
                         "value":false
                        }]
                }, 
                {
                 "id":24,
                 "properties":[
                        {
                         "name":"collides",
                         "type":"bool",
                         "value":false
                        }, 
                        {
                         "name":"kills",
                         "type":"bool",
                         "value":false
                        }]
                }, 
                {
                 "id":25,
                 "properties":[
                        {
                         "name":"collides",
                         "type":"bool",
                         "value":false
                        }, 
                        {
                         "name":"kills",
                         "type":"bool",
                         "value":false
                        }]
                }, 
                {
                 "id":26,
                 "properties":[
                        {
                         "name":"collides",
                         "type":"bool",
                         "value":false
                        }, 
                        {
                         "name":"kills",
                         "type":"bool",
                         "value":false
                        }]
                }, 
                {
                 "id":27,
                 "properties":[
                        {
                         "name":"collides",
                         "type":"bool",
                         "value":false
                        }, 
                        {
                         "name":"kills",
                         "type":"bool",
                         "value":false
                        }]
                }, 
                {
                 "id":28,
                 "properties":[
                        {
                         "name":"collides",
                         "type":"bool",
                         "value":false
                        }, 
                        {
                         "name":"kills",
                         "type":"bool",
                         "value":false
                        }]
                }, 
                {
                 "id":29,
                 "properties":[
                        {
                         "name":"collides",
                         "type":"bool",
                         "value":false
                        }, 
                        {
                         "name":"kills",
                         "type":"bool",
                         "value":true
                        }]
                }, 
                {
                 "id":30,
                 "properties":[
                        {
                         "name":"collides",
                         "type":"bool",
                         "value":false
                        }, 
                        {
                         "name":"kills",
                         "type":"bool",
                         "value":true
                        }]
                }, 
                {
                 "id":31,
                 "properties":[
                        {
                         "name":"collides",
                         "type":"bool",
                         "value":false
                        }, 
                        {
                         "name":"kills",
                         "type":"bool",
                         "value":false
                        }]
                },
            
                {
                 "id":32,
                 "properties":[
                        {
                         "name":"collides",
                         "type":"bool",
                         "value":false
                        }, 
                        {
                         "name":"kills",
                         "type":"bool",
                         "value":false
                        }]
                }, 
                {
                 "id":33,
                 "properties":[
                        {
                         "name":"collides",
                         "type":"bool",
                         "value":false
                        }, 
                        {
                         "name":"kills",
                         "type":"bool",
                         "value":false
                        }]
                }, 
                {
                 "id":34,
                 "properties":[
                        {
                         "name":"collides",
                         "type":"bool",
                         "value":false
                        }, 
                        {
                         "name":"kills",
                         "type":"bool",
                         "value":false
                        }]
                }, 
                {
                 "id":35,
                 "properties":[
                        {
                         "name":"collides",
                         "type":"bool",
                         "value":false
                        }, 
                        {
                         "name":"kills",
                         "type":"bool",
                         "value":false
                        }]
                }, 
                {
                 "id":36,
                 "properties":[
                        {
                         "name":"collides",
                         "type":"bool",
                         "value":false
                        }, 
                        {
                         "name":"kills",
                         "type":"bool",
                         "value":false
                        }]
                }, 
                {
                 "id":37,
                 "properties":[
                        {
                         "name":"collides",
                         "type":"bool",
                         "value":false
                        }, 
                        {
                         "name":"kills",
                         "type":"bool",
                         "value":false
                        }]
                }, 
                {
                 "id":38,
                 "properties":[
                        {
                         "name":"collides",
                         "type":"bool",
                         "value":false
                        }, 
                        {
                         "name":"kills",
                         "type":"bool",
                         "value":false
                        }]
                }, 
                {
                 "id":39,
                 "properties":[
                        {
                         "name":"collides",
                         "type":"bool",
                         "value":false
                        }, 
                        {
                         "name":"kills",
                         "type":"bool",
                         "value":false
                        }]
                }, 
                {
                 "id":40,
                 "properties":[
                        {
                         "name":"collides",
                         "type":"bool",
                         "value":false
                        }, 
                        {
                         "name":"kills",
                         "type":"bool",
                         "value":false
                        }]
                }, 
                {
                 "id":41,
                 "properties":[
                        {
                         "name":"collides",
                         "type":"bool",
                         "value":false
                        }, 
                        {
                         "name":"kills",
                         "type":"bool",
                         "value":false
                        }]
                }, 
                {
                 "id":42,
                 "properties":[
                        {
                         "name":"collides",
                         "type":"bool",
                         "value":false
                        }, 
                        {
                         "name":"kills",
                         "type":"bool",
                         "value":false
                        }]
                }, 
                {
                 "id":43,
                 "properties":[
                        {
                         "name":"collides",
                         "type":"bool",
                         "value":false
                        }, 
                        {
                         "name":"kills",
                         "type":"bool",
                         "value":false
                        }]
                }, 
                {
                 "id":44,
                 "properties":[
                        {
                         "name":"collides",
                         "type":"bool",
                         "value":false
                        }, 
                        {
                         "name":"kills",
                         "type":"bool",
                         "value":false
                        }]
                }, 
                {
                 "id":45,
                 "properties":[
                        {
                         "name":"collides",
                         "type":"bool",
                         "value":false
                        }, 
                        {
                         "name":"kills",
                         "type":"bool",
                         "value":false
                        }]
                }, 
                {
                 "id":46,
                 "properties":[
                        {
                         "name":"collides",
                         "type":"bool",
                         "value":false
                        }, 
                        {
                         "name":"kills",
                         "type":"bool",
                         "value":false
                        }]
                }, 
                {
                 "id":47,
                 "properties":[
                        {
                         "name":"collides",
                         "type":"bool",
                         "value":false
                        }, 
                        {
                         "name":"kills",
                         "type":"bool",
                         "value":false
                        }]
                }, 
                {
                 "id":48,
                 "properties":[
                        {
                         "name":"collides",
                         "type":"bool",
                         "value":false
                        }]
                }, 
                {
                 "id":49,
                 "properties":[
                        {
                         "name":"collides",
                         "type":"bool",
                         "value":false
                        }]
                }, 
                {
                 "id":50,
                 "properties":[
                        {
                         "name":"collides",
                         "type":"bool",
                         "value":false
                        }]
                }, 
                {
                 "id":51,
                 "properties":[
                        {
                         "name":"collides",
                         "type":"bool",
                         "value":false
                        }]
                }, 
                {
                 "id":52,
                 "properties":[
                        {
                         "name":"collides",
                         "type":"bool",
                         "value":false
                        }]
                }, 
                {
                 "id":53,
                 "properties":[
                        {
                         "name":"collides",
                         "type":"bool",
                         "value":false
                        }]
                }, 
                {
                 "id":54,
                 "properties":[
                        {
                         "name":"collides",
                         "type":"bool",
                         "value":false
                        }]
                }, 
                {
                 "id":55,
                 "properties":[
                        {
                         "name":"collides",
                         "type":"bool",
                         "value":false
                        }]
                }, 
                {
                 "id":56,
                 "properties":[
                        {
                         "name":"collides",
                         "type":"bool",
                         "value":false
                        }]
                }, 
                {
                 "id":57,
                 "properties":[
                        {
                         "name":"collides",
                         "type":"bool",
                         "value":false
                        }]
                }, 
                {
                 "id":58,
                 "properties":[
                        {
                         "name":"collides",
                         "type":"bool",
                         "value":false
                        }]
                }, 
                {
                 "id":59,
                 "properties":[
                        {
                         "name":"collides",
                         "type":"bool",
                         "value":false
                        }]
                }, 
                {
                 "id":60,
                 "properties":[
                        {
                         "name":"collides",
                         "type":"bool",
                         "value":false
                        }]
                }, 
                {
                 "id":61,
                 "properties":[
                        {
                         "name":"collides",
                         "type":"bool",
                         "value":false
                        }]
                }, 
                {
                 "id":62,
                 "properties":[
                        {
                         "name":"collides",
                         "type":"bool",
                         "value":false
                        }]
                }, 
                {
                 "id":63,
                 "properties":[
                        {
                         "name":"collides",
                         "type":"bool",
                         "value":false
                        }]
                }],
         "tilewidth":16,
         "transparentcolor":"#ff00ff"
        }],
 "tilewidth":16,
 "type":"map",
 "version":"1.10",
 "width":32
}